macgrind/__init__.py
macgrind/__main__.py
macgrind/definitions.py
macgrind/tools.py
macgrind-1.0.4.dist-info/LICENSE
macgrind-1.0.4.dist-info/METADATA
macgrind-1.0.4.dist-info/WHEEL
macgrind-1.0.4.dist-info/entry_points.txt
macgrind-1.0.4.dist-info/top_level.txt
macgrind-1.0.4.dist-info/RECORD
