Metadata-Version: 2.1
Name: macgrind
Version: 1.0.4
Summary: A containerized version of Valgrind for OSX.
Home-page: https://github.com/kokkonisd/macgrind
Author: Dimitri Kokkonis
Author-email: kokkonisd@gmail.com
License: UNKNOWN
Platform: UNKNOWN
Classifier: Programming Language :: Python :: 3
Classifier: License :: OSI Approved :: GNU General Public License v3 (GPLv3)
Classifier: Operating System :: OS Independent
Requires-Python: >=3.6
Requires-Dist: click
Requires-Dist: docker
